pragma_cli/__init__.py
pragma_cli/commands/__init__.py
pragma_cli/commands/auth.py
pragma_cli/commands/completions.py
pragma_cli/commands/config.py
pragma_cli/commands/dead_letter.py
pragma_cli/commands/ops.py
pragma_cli/commands/providers.py
pragma_cli/commands/resources.py
pragma_cli/config.py
pragma_cli/helpers.py
pragma_cli/main.py
pragma_cli/py.typed
pragmatiks_cli-0.15.1.dist-info/WHEEL
pragmatiks_cli-0.15.1.dist-info/entry_points.txt
pragmatiks_cli-0.15.1.dist-info/METADATA
pragmatiks_cli-0.15.1.dist-info/RECORD
