Metadata-Version: 2.3
Name: pragmatiks-cli
Version: 0.15.1
Summary: Command-line interface for Pragmatiks
Requires-Dist: typer>=0.15.3
Requires-Dist: pragmatiks-sdk>=0.18.0
Requires-Dist: pyyaml>=6.0.3
Requires-Dist: copier>=9.0.0
Requires-Dist: rich>=13.9.0
Requires-Python: >=3.13
